pybos/__init__.py
pybos/extraction.py
pybos/laplacian.py
pybos/physical_laws.py
pybos/reader.py
pybos/vector_calculus.py
pybos/version.py
pybos-0.1.1.dist-info/LICENSE
pybos-0.1.1.dist-info/METADATA
pybos-0.1.1.dist-info/WHEEL
pybos-0.1.1.dist-info/top_level.txt
pybos-0.1.1.dist-info/RECORD
