Metadata-Version: 2.1
Name: pybos
Version: 0.1.1
Summary: BOS library
Home-page: https://gitlab.coria-cfd.fr/pouxa/pybos/
Author: CNRS, CORIA UMR 6614
Author-email: alexandre.poux@coria.fr
License: GPLV3
Download-URL: https://gitlab.coria-cfd.fr/pouxa/pybos/repository/archive.zip?ref=master
Keywords: BOS,Background Oriented Schlieren,Refractive Index Measurement,Tomographic Reconstruction
Platform: UNKNOWN
Classifier: Development Status :: 3 - Alpha
Classifier: Environment :: Console
Classifier: Framework :: Jupyter
Classifier: Framework :: Matplotlib
Classifier: Intended Audience :: Science/Research
Classifier: License :: OSI Approved :: GNU General Public License v3 or later (GPLv3+)
Classifier: Natural Language :: English
Classifier: Operating System :: OS Independent
Classifier: Programming Language :: Python :: 3 :: Only
Classifier: Programming Language :: Python :: 3.7
Classifier: Programming Language :: Python :: 3.8
Classifier: Programming Language :: Python :: 3.9
Classifier: Topic :: Education
Classifier: Topic :: Scientific/Engineering :: Image Processing
Classifier: Topic :: Scientific/Engineering :: Physics
Classifier: Typing :: Typed
Requires-Python: >=3.7
License-File: LICENSE
Requires-Dist: numpy
Requires-Dist: matplotlib
Requires-Dist: scipy
Requires-Dist: pint
Requires-Dist: future
Requires-Dist: fipy
Requires-Dist: pandas
Requires-Dist: xarray[accel]
Requires-Dist: numexpr
Provides-Extra: complete
Requires-Dist: pyabel ; extra == 'complete'
Requires-Dist: scikit-image ; extra == 'complete'
Requires-Dist: jupyterlab ; extra == 'complete'
Requires-Dist: ipykernel ; extra == 'complete'
Requires-Dist: ipympl ; extra == 'complete'
Requires-Dist: pytest ; extra == 'complete'
Requires-Dist: pytest-html ; extra == 'complete'
Requires-Dist: pytest-timeout ; extra == 'complete'
Requires-Dist: pytest-cov ; extra == 'complete'
Requires-Dist: pytest-sugar ; extra == 'complete'
Requires-Dist: pytest-icdiff ; extra == 'complete'
Provides-Extra: dev
Requires-Dist: pyabel ; extra == 'dev'
Requires-Dist: scikit-image ; extra == 'dev'
Requires-Dist: jupyterlab ; extra == 'dev'
Requires-Dist: ipykernel ; extra == 'dev'
Requires-Dist: ipympl ; extra == 'dev'
Requires-Dist: pytest ; extra == 'dev'
Requires-Dist: pytest-html ; extra == 'dev'
Requires-Dist: pytest-timeout ; extra == 'dev'
Requires-Dist: pytest-cov ; extra == 'dev'
Requires-Dist: pytest-sugar ; extra == 'dev'
Requires-Dist: pytest-icdiff ; extra == 'dev'
Requires-Dist: black[jupyter] ; extra == 'dev'
Requires-Dist: isort[requirements_deprecated_finder] ; extra == 'dev'
Requires-Dist: mypy ; extra == 'dev'
Requires-Dist: pandas-stubs ; extra == 'dev'
Requires-Dist: flake8 ; extra == 'dev'
Requires-Dist: pyproject-flake8 ; extra == 'dev'
Requires-Dist: flake8-bugbear ; extra == 'dev'
Requires-Dist: flake8-builtins ; extra == 'dev'
Requires-Dist: flake8-comprehensions ; extra == 'dev'
Requires-Dist: flake8-strict ; extra == 'dev'
Requires-Dist: pandas-vet ; extra == 'dev'
Requires-Dist: flake8-use-fstring ; extra == 'dev'
Requires-Dist: flake8-copyright ; extra == 'dev'
Requires-Dist: flake8-annotations ; extra == 'dev'
Requires-Dist: flake8-annotations-complexity ; extra == 'dev'
Requires-Dist: flake8-annotations-coverage ; extra == 'dev'
Requires-Dist: pydocstyle[toml] ; extra == 'dev'
Requires-Dist: pylint ; extra == 'dev'
Provides-Extra: jupyter
Requires-Dist: jupyterlab ; extra == 'jupyter'
Requires-Dist: ipykernel ; extra == 'jupyter'
Requires-Dist: ipympl ; extra == 'jupyter'
Provides-Extra: test
Requires-Dist: pytest ; extra == 'test'
Requires-Dist: pytest-html ; extra == 'test'
Requires-Dist: pytest-timeout ; extra == 'test'
Requires-Dist: pytest-cov ; extra == 'test'
Requires-Dist: pytest-sugar ; extra == 'test'
Requires-Dist: pytest-icdiff ; extra == 'test'
Provides-Extra: transform
Requires-Dist: pyabel ; extra == 'transform'
Requires-Dist: scikit-image ; extra == 'transform'
